nkparser/__init__.py
nkparser/help.py
nkparser/load.py
nkparser/parse.py
nkparser/utils.py
nkparser/config/cal.json
nkparser/config/entry.json
nkparser/config/history.json
nkparser/config/horse.json
nkparser/config/odds.json
nkparser/config/race.json
nkparser/config/race_db.json
nkparser/config/result.json
test/__init__.py
test/test_entry.py
test/test_horse.py
test/test_odds.py
test/test_result.py
test/test_utils.py
nkparser-1.5.6.dist-info/LICENSE
nkparser-1.5.6.dist-info/METADATA
nkparser-1.5.6.dist-info/WHEEL
nkparser-1.5.6.dist-info/top_level.txt
nkparser-1.5.6.dist-info/RECORD
