Metadata-Version: 2.1
Name: nkparser
Version: 1.5.6
Summary: nkparser is a simple scraping library for netkeiba.com
Home-page: https://github.com/new-village/nkparser
Author: new-village
License-File: LICENSE
Requires-Dist: requests
Requires-Dist: bs4
Requires-Dist: jq
